cloudscrapersafe/__init__.py
cloudscrapersafe/cloudflare.py
cloudscrapersafe/exceptions.py
cloudscrapersafe/help.py
cloudscrapersafe/captcha/2captcha.py
cloudscrapersafe/captcha/9kw.py
cloudscrapersafe/captcha/__init__.py
cloudscrapersafe/captcha/anticaptcha.py
cloudscrapersafe/captcha/capmonster.py
cloudscrapersafe/captcha/capsolver.py
cloudscrapersafe/captcha/deathbycaptcha.py
cloudscrapersafe/interpreters/__init__.py
cloudscrapersafe/interpreters/chakracore.py
cloudscrapersafe/interpreters/encapsulated.py
cloudscrapersafe/interpreters/js2py.py
cloudscrapersafe/interpreters/jsunfuck.py
cloudscrapersafe/interpreters/native.py
cloudscrapersafe/interpreters/nodejs.py
cloudscrapersafe/interpreters/v8.py
cloudscrapersafe/user_agent/__init__.py
cloudscrapersafe/user_agent/browsers.json
cloudscrapersafe-3.1.1.dist-info/licenses/LICENSE
cloudscrapersafe-3.1.1.dist-info/METADATA
cloudscrapersafe-3.1.1.dist-info/WHEEL
cloudscrapersafe-3.1.1.dist-info/top_level.txt
cloudscrapersafe-3.1.1.dist-info/RECORD
