Metadata-Version: 2.4
Name: cloudscrapersafe
Version: 3.1.1
Summary: Cloudscraper v2 modificado para bypass de Cloudflare con soporte para proxy y stealth.
Home-page: https://github.com/venomous/cloudscraper
Author: VeNoMouS
Author-email: VeNoMouS <venom@cloudscraper.io>
License: MIT
Project-URL: Homepage, https://github.com/VeNoMouS/cloudscraper
Project-URL: Repository, https://github.com/VeNoMouS/cloudscraper
Project-URL: Issues, https://github.com/VeNoMouS/cloudscraper/issues
Keywords: cloudflare,scraping,bypass,anti-bot,webscraper,waf,iuam
Classifier: Development Status :: 5 - Production/Stable
Classifier: Intended Audience :: Developers
Classifier: Natural Language :: English
Classifier: License :: OSI Approved :: MIT License
Classifier: Operating System :: OS Independent
Classifier: Programming Language :: Python
Classifier: Programming Language :: Python :: 3
Classifier: Programming Language :: Python :: 3.8
Classifier: Programming Language :: Python :: 3.9
Classifier: Programming Language :: Python :: 3.10
Classifier: Programming Language :: Python :: 3.11
Classifier: Programming Language :: Python :: 3.12
Classifier: Topic :: Internet :: WWW/HTTP
Classifier: Topic :: Software Development :: Libraries :: Python Modules
Requires-Python: >=3.8
License-File: LICENSE
Requires-Dist: requests>=2.31.0
Requires-Dist: requests-toolbelt>=1.0.0
Requires-Dist: pyparsing>=3.1.0
Requires-Dist: pyOpenSSL>=24.0.0
Requires-Dist: pycryptodome>=3.20.0
Requires-Dist: websocket-client>=1.7.0
Requires-Dist: js2py>=0.74
Requires-Dist: brotli>=1.1.0
Requires-Dist: certifi>=2024.2.2
Requires-Dist: pyjwt>=2.10.1
Dynamic: author
Dynamic: home-page
Dynamic: license-file
